bms_transformer/__init__.py
bms_transformer/megacolumn.py
bms_transformer-0.0.1.dist-info/LICENSE
bms_transformer-0.0.1.dist-info/METADATA
bms_transformer-0.0.1.dist-info/WHEEL
bms_transformer-0.0.1.dist-info/top_level.txt
bms_transformer-0.0.1.dist-info/RECORD
