Metadata-Version: 2.1
Name: bms-transformer
Version: 0.0.1
Summary: for transforming columns
Home-page: https://github.com/naexuis/bms
Author: Marcus Hilliard
Author-email: marcus.hilliard@benchmarkanalytics.com
License: UNKNOWN
Platform: UNKNOWN
Classifier: Programming Language :: Python :: 3
Classifier: License :: OSI Approved :: MIT License
Classifier: Operating System :: OS Independent
Requires-Python: >=3.7
License-File: LICENSE
